{"uid":"AMANR5L17PO838901B1906P1D1N002889","chronotag":"1761202853887","legislature":"17","identification":{"numeroLong":"I-2889","numeroOrdreDepot":"2889","prefixeOrganeExamen":"AN","numeroRect":"0"},"examenRef":"EXANR5L17PO838901B1906P1D1","texteLegislatifRef":"PRJLANR5L17B1906","triAmendement":"aoaaaaaaaaaaaaaaaaaaaaaaaaaaaaaaaaaaaaaaaaaaaaaaaazzzzzzzzzzzzzzzzzzzzzzu","cardinaliteAmdtMultiples":"1","amendementParentRef":{},"signataires":{"auteur":{"typeAuteur":"D\u00e9put\u00e9","gouvernementRef":{},"acteurRef":"PA721202","groupePolitiqueRef":"PO845413","auteurRapporteurOrganeRef":{}},"cosignataires":{"acteurRef":["PA795228","PA793262","PA794906","PA794138","PA795588","PA795084","PA842105","PA841657","PA720430","PA793772","PA795616","PA793444","PA794938","PA795318","PA841023","PA796090","PA793912","PA842187","PA842037","PA791812","PA793736","PA795136","PA793464","PA842155","PA795200","PA795844","PA841251","PA794786","PA794870","PA796070","PA795310","PA794478","PA841947","PA794082","PA794130","PA720846","PA841729","PA795516","PA841515","PA795672","PA795108","PA795298","PA791824","PA842029","PA793532","PA795746","PA342384","PA795422","PA794686","PA841215","PA795482","PA610654","PA841191","PA721960","PA793872","PA720892","PA817211","PA793756","PA796062","PA719578","PA721062","PA841845","PA795982","PA795466","PA793744","PA720952","PA794106","PA794166","PA795164","PA795596"]},"suffixe":{},"libelle":" M.\u0026#160;Coquerel,  Mme\u0026#160;Abomangoli, M.\u0026#160;Alexandre, M.\u0026#160;Amard, Mme\u0026#160;Amiot, Mme\u0026#160;Amrani, M.\u0026#160;Arenas, M.\u0026#160;Arnault, Mme\u0026#160;Belouassa-Cherifi, M.\u0026#160;Bernalicis, M.\u0026#160;Bex, M.\u0026#160;Bilongo, M.\u0026#160;Bompard, M.\u0026#160;Boumertit, M.\u0026#160;Boyard, M.\u0026#160;Cadalen, M.\u0026#160;Caron, M.\u0026#160;Carri\u0026#232;re, Mme\u0026#160;Cathala, M.\u0026#160;Cernon, Mme\u0026#160;Chikirou, M.\u0026#160;Clouet, M.\u0026#160;Coulomme, M.\u0026#160;Delogu, M.\u0026#160;Diouara, Mme\u0026#160;Dufour, Mme\u0026#160;Erodi, Mme\u0026#160;Feld, M.\u0026#160;Fernandes, Mme\u0026#160;Ferrer, M.\u0026#160;Gaillard, Mme\u0026#160;Guett\u0026#233;, M.\u0026#160;Guiraud, Mme\u0026#160;Hamdane, Mme\u0026#160;Hignet, M.\u0026#160;Kerbrat, M.\u0026#160;Lachaud, M.\u0026#160;Lahmar, M.\u0026#160;Laisney, M.\u0026#160;Le\u0026#160;Coq, M.\u0026#160;Le\u0026#160;Gall, Mme\u0026#160;Leboucher, M.\u0026#160;Legavre, Mme\u0026#160;Legrain, Mme\u0026#160;Lejeune, Mme\u0026#160;Lepvraud, M.\u0026#160;L\u0026#233;aument, Mme\u0026#160;\u0026#201;lisa\u0026#160;Martin, M.\u0026#160;Maudet, Mme\u0026#160;Maximi, Mme\u0026#160;Mesmeur, Mme\u0026#160;Manon\u0026#160;Meunier, M.\u0026#160;Nilor, Mme\u0026#160;Nosb\u0026#233;, Mme\u0026#160;Obono, Mme\u0026#160;Oziol, Mme\u0026#160;Panot, M.\u0026#160;Pilato, M.\u0026#160;Piquemal, M.\u0026#160;Portes, M.\u0026#160;Prud\u0026apos;homme, M.\u0026#160;Ratenon, M.\u0026#160;Saint-Martin, M.\u0026#160;Saintoul, Mme\u0026#160;Soudais, Mme\u0026#160;Stambach-Terrenoir, M.\u0026#160;Aur\u0026#233;lien\u0026#160;Tach\u0026#233;, Mme\u0026#160;Taurinya, M.\u0026#160;Tavel, Mme\u0026#160;Trouv\u0026#233; et M.\u0026#160;Vannier"},"pointeurFragmentTexte":{"partieAmendableRef":{},"division":{"titre":"Article 3","articleDesignationCourte":"APR\u00c8S ART. 3","articleDesignation":"APR\u00c8S L\u0027ARTICLE 3, ins\u00e9rer l\u0027article suivant:","type":"ARTICLE","avant_A_Apres":"Apr\u00e8s","divisionRattachee":{},"articleAdditionnel":"true","chapitreAdditionnel":"false","urlDivisionTexteVise":"\/17\/textes\/1906A.asp#D_Article_3"},"amendementStandard":{"alinea":{}}},"corps":{"cartoucheInformatif":"Sous r\u00e9serve de son traitement par les services de l\u0027Assembl\u00e9e nationale et de sa recevabilit\u00e9","contenuAuteur":{"dispositif":"\u003Cp style=\u0022text-align: justify;\u0022\u003EI.\u0026nbsp;\u0026#x2013;\u0026nbsp;Le code g\u0026#x00E9;n\u0026#x00E9;ral des imp\u0026#x00F4;ts est ainsi modifi\u0026#x00E9; :\u0026nbsp;\u003C\/p\u003E\u003Cp style=\u0022text-align: justify;\u0022\u003E1\u0026#x00B0;\u0026nbsp;Apr\u0026#x00E8;s l\u0026#x2019;article\u0026nbsp;779, il est ins\u0026#x00E9;r\u0026#x00E9; un article\u0026nbsp;779\u0026nbsp;bis ainsi r\u0026#x00E9;dig\u0026#x00E9;\u0026nbsp;:\u003C\/p\u003E\u003Cp\u003E\u0026#x00AB;\u0026nbsp;Art 779\u0026nbsp;bis.\u0026nbsp;\u0026#x2013; I. \u0026#x2013;\u0026nbsp;Les droits de mutation \u0026#x00E0; titre gratuit dus \u0026#x00E0; raison des successions sont r\u0026#x00E9;duits dans les conditions suivantes\u0026nbsp;:\u003C\/p\u003E\u003Cp\u003E1\u0026#x00B0;\u0026nbsp;Une r\u0026#x00E9;duction de quinze pour cent est appliqu\u0026#x00E9;e lorsque l\u0026#x2019;h\u0026#x00E9;ritier est \u0026#x00E2;g\u0026#x00E9; de dix-huit \u0026#x00E0; vingt-neuf ans r\u0026#x00E9;volus au jour de la donation\u0026nbsp;;\u003C\/p\u003E\u003Cp\u003E2\u0026#x00B0;\u0026nbsp;Une r\u0026#x00E9;duction de cinq pour cent est appliqu\u0026#x00E9;e lorsque l\u0026#x2019;h\u0026#x00E9;ritier est \u0026#x00E2;g\u0026#x00E9; de trente \u0026#x00E0; trente-neuf ans r\u0026#x00E9;volus au jour de la donation.\u003C\/p\u003E\u003Cp\u003E\u0026#x00AB;\u0026nbsp;II. La r\u0026#x00E9;duction s\u0026#x2019;applique sur le montant des droits calcul\u0026#x00E9;s apr\u0026#x00E8;s application des abattements et du tarif mentionn\u0026#x00E9;s \u0026#x00E0; l\u0026#x2019;article\u0026nbsp;777 du pr\u0026#x00E9;sent code.\u003C\/p\u003E\u003Cp\u003E\u0026#x00AB;\u0026nbsp;III. Les r\u0026#x00E9;ductions mentionn\u0026#x00E9;es au pr\u0026#x00E9;sent article ne sont ni cumulables entre elles ni avec d\u0026#x2019;autres r\u0026#x00E9;ductions pr\u0026#x00E9;vues par le pr\u0026#x00E9;sent code, sauf disposition expresse contraire.\u0026nbsp;\u0026#x00BB;\u003C\/p\u003E\u003Cp style=\u0022text-align: justify;\u0022\u003E2\u0026#x00B0; Au deuxi\u0026#x00E8;me alin\u0026#x00E9;a de l\u0026#x2019;article\u0026nbsp;784, les mots\u0026nbsp;: \u0026#x00AB;\u0026nbsp;,\u0026nbsp;\u0026#x00E0; l\u0026#x2019;exception de celles pass\u0026#x00E9;es depuis plus de quinze ans,\u0026nbsp;\u0026#x00BB; sont supprim\u0026#x00E9;s.\u003C\/p\u003E\u003Cp style=\u0022text-align: justify;\u0022\u003EII.\u0026nbsp;\u0026#x2013;\u0026nbsp;La perte de recettes pour l\u0026#x2019;\u0026#x00C9;tat est compens\u0026#x00E9;e \u0026#x00E0; due concurrence par la cr\u0026#x00E9;ation d\u0026#x2019;une taxe additionnelle \u0026#x00E0; l\u0026#x2019;accise sur les tabacs pr\u0026#x00E9;vue au chapitre IV du titre I\u003Csup\u003Eer\u003C\/sup\u003E du livre III du code des impositions sur les biens et services.\u003C\/p\u003E","avantAppel":{},"exposeSommaire":"\u003Cp\u003EPar cet amendement de repli, le groupe parlementaire LFI propose de comptabiliser l\u0026#x2019;h\u0026#x00E9;ritage tout au long de la vie au lieu de r\u0026#x00E9;initialiser le d\u0026#x00E9;compte arbitrairement tous les quinze ans. Afin de favoriser les transmissions \u0026#x00E0; un \u0026#x00E2;ge o\u0026#x00F9; cette derni\u0026#x00E8;re est la plus utile pour l\u0026#x2019;h\u0026#x00E9;ritier, cet amendement s\u0026#x2019;accompagne d\u0026#x2019;une d\u0026#x00E9;cote pour les h\u0026#x00E9;ritages \u0026#x00E0; destination des personnes de 18 \u0026#x00E0; 39 ans.\u003C\/p\u003E\u003Cp\u003EAujourd\u0026#x2019;hui, le patrimoine est fortement concentr\u0026#x00E9; dans notre pays. Les 10% les plus fortun\u0026#x00E9;s d\u0026#x00E9;tiennent la moiti\u0026#x00E9; du patrimoine national. L\u0026#x2019;h\u0026#x00E9;ritage est ainsi lui aussi tr\u0026#x00E8;s in\u0026#x00E9;galitaire. Pr\u0026#x00E8;s de la moiti\u0026#x00E9; des m\u0026#x00E9;nages fran\u0026#x00E7;ais ne touchent aucun h\u0026#x00E9;ritage au cours de leur vie et 80 % ne re\u0026#x00E7;oivent aucune donation du vivant de leurs proches.\u003C\/p\u003E\u003Cp\u003EEn plus de reproduire les in\u0026#x00E9;galit\u0026#x00E9;s, l\u0026#x2019;h\u0026#x00E9;ritage, aujourd\u0026#x2019;hui, ne permet plus la transmission du patrimoine aux jeunes g\u0026#x00E9;n\u0026#x00E9;rations. Comme le note le CAE, l\u0026#x2019;\u0026#x00E2;ge moyen des h\u0026#x00E9;ritiers est de 50 ans aujourd\u0026#x2019;hui, contre 30 ans au d\u0026#x00E9;but du si\u0026#x00E8;cle dernier. On h\u0026#x00E9;rite donc de plus en plus \u0026#x00E0; un \u0026#x00E2;ge avanc\u0026#x00E9; o\u0026#x00F9; la situation sociale des personnes est stable (logement, emploi...). L\u0026#x2019;h\u0026#x00E9;ritage consolide ainsi un patrimoine existant au lieu d\u0026#x2019;\u0026#x00EA;tre un tremplin au d\u0026#x00E9;but de la vie active.\u003C\/p\u003E\u003Cp\u003EJamais la France dans son histoire n\u0026#x2019;a connu une jeunesse, dans sa grande majorit\u0026#x00E9;, aussi pr\u0026#x00E9;caris\u0026#x00E9;e, mais aussi instruite que la n\u0026#x00F4;tre. \u003Cbr\u003EPr\u0026#x00E9;caris\u0026#x00E9;e par les r\u0026#x00E9;formes sociales violentes qu\u0026#x2019;\u0026#x00E0; mis en \u0026#x0153;uvre Macron depuis 2017 (r\u0026#x00E9;duction de 5 euros des APL, suppression du repas CROUS \u0026#x00E0; 1 euro, sous dotation en logement \u0026#x00E9;tudiant\u0026#x2026;) et par un march\u0026#x00E9; du travail exsangue. Le taux de pauvret\u0026#x00E9; des moins des 18-29 ans est ainsi le plus fort des toutes les cat\u0026#x00E9;gories d\u0026#x2019;\u0026#x00E2;ges et atteint 17.5%, plus de deux points au-dessus de la moyenne de la population. En 2024, le taux de ch\u0026#x00F4;mage des 15-24 ans atteint 18,8 % en moyenne sur l\u0027ann\u0026#x00E9;e, contre 6,7 % chez les 25-49 ans. Notre jeunesse aspire \u0026#x00E0; juste titre de pouvoir se loger dignement alors que les prix de l\u0026#x2019;immobilier et les salaires se sont largement d\u0026#x00E9;corr\u0026#x00E9;l\u0026#x00E9;s au cours des 30 derni\u0026#x00E8;res ann\u0026#x00E9;es.\u003C\/p\u003E\u003Cp\u003EAlors qu\u0027en 1980 la moyenne d\u0027\u0026#x00E2;ge des h\u0026#x00E9;ritiers en ligne directe \u0026#x00E9;tait de 43 ans, elle est de 52 ans en 2020. Les h\u0026#x00E9;ritiers sont d\u0026#x00E9;sormais des personnes bien \u0026#x00E9;tablies dans la vie, pour qui ce surplus de patrimoine n\u0026#x2019;est pas d\u0026#x2019;une grande utilit\u0026#x00E9;. Et pourtant la transmission d\u0026#x2019;un patrimoine leur aurait \u0026#x00E9;t\u0026#x00E9; particuli\u0026#x00E8;rement utile lors e leur entr\u0026#x00E9;e dans la vie active !\u003C\/p\u003E\u003Cp\u003ENotre amendement propose de supprimer l\u0026#x2019;abattement existant sur les sommes transmises tous les 15 ans, et de le remplacer par une r\u0026#x00E9;duction d\u0026#x2019;imp\u0026#x00F4;t sur les sommes re\u0026#x00E7;ues entre 18 et 39 ans. Cette r\u0026#x00E9;duction d\u0026#x2019;imp\u0026#x00F4;t serait d\u0026#x00E9;gressive plus l\u0026#x2019;\u0026#x00E2;ge avan\u0026#x00E7;ant pour inciter aux donations aux jeunes g\u0026#x00E9;n\u0026#x00E9;rations, d\u0026#x00E8;s leurs entr\u0026#x00E9;es dans la vie active.\u003C\/p\u003E\u003Cp\u003E\u0026nbsp;\u003C\/p\u003E","annexeExposeSommaire":{}}},"cycleDeVie":{"dateDepot":"2025-10-22","datePublication":{},"soumisArticle40":"true","etatDesTraitements":{"etat":{"code":"ET","libelle":"En traitement"},"sousEtat":{}},"dateSort":{},"sort":{}},"representations":{"representation":{"nom":"PDF","typeMime":{"type":"application","subType":"PDF"},"statutRepresentation":{"verbatim":"true","canonique":"true","officielle":"true","transcription":"false","enregistrement":"false"},"repSource":{},"offset":{},"contenu":{"documentURI":"\/base\/AMANR5L17PO838901B1906P1D1N002889?format=pdf"},"dateDispoRepresentation":{}}},"seanceDiscussionRef":{},"article99":"false","loiReference":{},"discussionCommune":{},"discussionIdentique":{},"accordGouvernementDepotHorsDelai":"Sans objet"}