{"uid":"AMANR5L17PO59048B1906P1D1N001854","chronotag":"1760975564004","legislature":"17","identification":{"numeroLong":"I-CF1854","numeroOrdreDepot":"1854","prefixeOrganeExamen":"CION_FIN","numeroRect":"0"},"examenRef":"EXANR5L17PO59048B1906P1D1","texteLegislatifRef":"PRJLANR5L17B1906","triAmendement":"awaaaaaaaaaaaaaaaaaaaaaaaaaaaaaaaaaaaaaaaaaaaaaaaaaaik","cardinaliteAmdtMultiples":"1","amendementParentRef":{},"signataires":{"auteur":{"typeAuteur":"Rapporteur","gouvernementRef":{},"acteurRef":"PA346782","groupePolitiqueRef":"PO845425","auteurRapporteurOrganeRef":{}},"cosignataires":{},"suffixe":{},"libelle":" M.\u0026#160;Juvin, rapporteur g\u0026#233;n\u0026#233;ral"},"pointeurFragmentTexte":{"partieAmendableRef":{},"division":{"titre":"ARTICLE 5","articleDesignationCourte":"ART. 5","articleDesignation":"ARTICLE 5","type":"ARTICLE","avant_A_Apres":"A","divisionRattachee":{},"articleAdditionnel":"false","chapitreAdditionnel":"false","urlDivisionTexteVise":"\/17\/textes\/1906A.asp#D_ARTICLE_5"},"amendementStandard":{"alinea":{"avant_A_Apres":{},"numero":"6","alineaDesignation":"Alin\u00e9a 6"}}},"corps":{"cartoucheInformatif":{},"contenuAuteur":{"dispositif":"\u003Cp\u003ESupprimer l\u0026#x2019;alin\u0026#x00E9;a 6.\u003C\/p\u003E","avantAppel":{},"exposeSommaire":"\u003Cp style=\u0022text-align: justify;\u0022\u003ECet amendement vise \u0026#x00E0; supprimer l\u0026#x2019;assujettissement \u0026#x00E0; l\u0026#x2019;imp\u0026#x00F4;t sur le revenu des traitements attach\u0026#x00E9;s \u0026#x00E0; la l\u0026#x00E9;gion d\u0026#x2019;honneur et \u0026#x00E0; la m\u0026#x00E9;daille militaire.\u003C\/p\u003E\u003Cp style=\u0022text-align: justify;\u0022\u003ECes traitements annuels sont\u0026nbsp;:\u003C\/p\u003E\u003Cp style=\u0022text-align: justify;\u0022\u003E\u0026#x2013;\u0026nbsp;entre 6,10\u0026nbsp;\u0026#x20AC; et 36,59\u0026nbsp;\u0026#x20AC; pour la l\u0026#x00E9;gion d\u0026#x2019;honneur\u0026nbsp;;\u003C\/p\u003E\u003Cp style=\u0022text-align: justify;\u0022\u003E\u0026#x2013;\u0026nbsp;de 4,57\u0026nbsp;\u0026#x20AC; pour la m\u0026#x00E9;daille militaire.\u003C\/p\u003E\u003Cp style=\u0022text-align: justify;\u0022\u003ECes traitements symboliques constituent ainsi une marque d\u0026#x2019;honneur plus qu\u0026#x2019;une source de revenu. Leur montant, modeste, n\u0026#x2019;a pas vocation \u0026#x00E0; \u0026#x00EA;tre int\u0026#x00E9;gr\u0026#x00E9; dans l\u0026#x2019;assiette de l\u0026#x2019;imp\u0026#x00F4;t sur le revenu.\u0026nbsp;\u003C\/p\u003E\u003Cp style=\u0022text-align: justify;\u0022\u003ELa fiscalisation de ces indemnit\u0026#x00E9;s, telle que propos\u0026#x00E9;e par le pr\u0026#x00E9;sent article, aurait un impact budg\u0026#x00E9;taire limit\u0026#x00E9; compte tenu du nombre restreint de b\u0026#x00E9;n\u0026#x00E9;ficiaires et du montant modique des traitements concern\u0026#x00E9;s, mais elle porterait atteinte \u0026#x00E0; une valeur symbolique forte\u0026nbsp;: celle de la reconnaissance de la Nation \u0026#x00E0; l\u0026#x2019;\u0026#x00E9;gard de ceux qui l\u0026#x2019;ont servie avec m\u0026#x00E9;rite.\u003C\/p\u003E","annexeExposeSommaire":{}}},"cycleDeVie":{"dateDepot":"2025-10-19","datePublication":"2025-10-20","soumisArticle40":"false","etatDesTraitements":{"etat":{"code":"AC","libelle":"A discuter"},"sousEtat":{}},"dateSort":{},"sort":{}},"representations":{"representation":{"nom":"PDF","typeMime":{"type":"application","subType":"PDF"},"statutRepresentation":{"verbatim":"true","canonique":"true","officielle":"true","transcription":"false","enregistrement":"false"},"repSource":{},"offset":{},"contenu":{"documentURI":"\/base\/AMANR5L17PO59048B1906P1D1N001854?format=pdf"},"dateDispoRepresentation":{}}},"seanceDiscussionRef":{},"article99":"false","loiReference":{"codeLoi":"0","divisionCodeLoi":{}},"discussionCommune":{"idDiscussion":"32429","typePosition":"Milieu"},"discussionIdentique":{"idDiscussion":"81697","typePosition":"Premier"},"accordGouvernementDepotHorsDelai":"Sans objet"}