{"uid":"AMANR5L17PO59048B1906P1D1N000035","chronotag":"1760797063188","legislature":"17","identification":{"numeroLong":"I-CF35","numeroOrdreDepot":"35","prefixeOrganeExamen":"CION_FIN","numeroRect":"0"},"examenRef":"EXANR5L17PO59048B1906P1D1","texteLegislatifRef":"PRJLANR5L17B1906","triAmendement":"ikaaaaaaaaaaaaaaaaaaaaaaaaaaaaaaaaaaaaaaaaaaaaaaaad","cardinaliteAmdtMultiples":"1","amendementParentRef":{},"signataires":{"auteur":{"typeAuteur":"D\u00e9put\u00e9","gouvernementRef":{},"acteurRef":"PA720256","groupePolitiqueRef":"PO845454","auteurRapporteurOrganeRef":{}},"cosignataires":{},"suffixe":{},"libelle":" Mme\u0026#160;Bannier"},"pointeurFragmentTexte":{"partieAmendableRef":{},"division":{"titre":"ARTICLE 30","articleDesignationCourte":"APR\u00c8S ART. 30","articleDesignation":"APR\u00c8S L\u0027ARTICLE 30, ins\u00e9rer l\u0027article suivant:","type":"ARTICLE","avant_A_Apres":"Apr\u00e8s","divisionRattachee":{},"articleAdditionnel":"true","chapitreAdditionnel":"false","urlDivisionTexteVise":"\/17\/textes\/1906A.asp#D_ARTICLE_30"},"amendementStandard":{"alinea":{}}},"corps":{"cartoucheInformatif":"Sous r\u00e9serve de son traitement par les services de l\u0027Assembl\u00e9e nationale et de sa recevabilit\u00e9","contenuAuteur":{"dispositif":"\u003Cp style=\u0022text-align: justify;\u0022\u003EI.\u0026nbsp;\u0026#x2013;\u0026nbsp;\u0026#x00C0; la fin du premier alin\u0026#x00E9;a du\u0026nbsp;1 du\u0026nbsp;III de l\u0026#x2019;article\u0026nbsp;220\u0026nbsp;\u003Ci\u003Equaterdecies\u003C\/i\u003E du code g\u0026#x00E9;n\u0026#x00E9;ral des imp\u0026#x00F4;ts, l\u0026#x2019;ann\u0026#x00E9;e\u0026nbsp;: \u0026#x00AB;\u0026nbsp;2026\u0026nbsp;\u0026#x00BB; est remplac\u0026#x00E9;e par l\u0026#x2019;ann\u0026#x00E9;e\u0026nbsp;: \u0026#x00AB;\u0026nbsp;2031\u0026nbsp;\u0026#x00BB;.\u003C\/p\u003E\u003Cp style=\u0022text-align: justify;\u0022\u003EII.\u0026nbsp;\u0026#x2013;\u0026nbsp;Le I n\u0026#x2019;est applicable qu\u0026#x2019;aux sommes venant en d\u0026#x00E9;duction de l\u0026#x2019;imp\u0026#x00F4;t d\u0026#x00FB;.\u003C\/p\u003E\u003Cp style=\u0022text-align: justify;\u0022\u003EIII.\u0026nbsp;\u0026#x2013;\u0026nbsp;La perte de recettes pour l\u0026#x2019;\u0026#x00C9;tat est compens\u0026#x00E9;e \u0026#x00E0; due concurrence par la cr\u0026#x00E9;ation d\u0026#x2019;une taxe additionnelle \u0026#x00E0; l\u0026#x2019;accise sur les tabacs pr\u0026#x00E9;vue au chapitre\u0026nbsp;IV du titre\u0026nbsp;I\u003Csup\u003Eer\u003C\/sup\u003E du livre\u0026nbsp;III du code des impositions sur les biens et services.\u003C\/p\u003E","avantAppel":{},"exposeSommaire":"\u003Cp style=\u0022text-align: justify;\u0022\u003ELe cr\u0026#x00E9;dit d\u0026#x2019;imp\u0026#x00F4;t international\u0026nbsp;(C2I) concerne les films et s\u0026#x00E9;ries d\u0026#x2019;initiative \u0026#x00E9;trang\u0026#x00E8;re dont toute ou une partie de la fabrication a lieu en France. Il b\u0026#x00E9;n\u0026#x00E9;ficie aux soci\u0026#x00E9;t\u0026#x00E9;s \u0026#x00E9;tablies en France qui assurent la production concr\u0026#x00E8;te d\u0026#x2019;une \u0026#x0153;uvre pour le compte d\u0026#x2019;un commanditaire \u0026#x00E9;tranger. Il a d\u0026#x00E9;montr\u0026#x00E9; son efficacit\u0026#x00E9; depuis sa cr\u0026#x00E9;ation en 2009 et a atteint un niveau record en 2023 avec 629 millions d\u0026#x2019;euros de d\u0026#x00E9;penses \u0026#x00E9;ligibles effectu\u0026#x00E9;es en France, auxquelles s\u0026#x2019;ajoutent 324 millions d\u0026#x2019;euros de d\u0026#x00E9;penses directes non \u0026#x00E9;ligibles.\u003C\/p\u003E\u003Cp style=\u0022text-align: justify;\u0022\u003ELe CNC estime \u0026#x00E9;galement \u0026#x00E0; 925 millions d\u0026#x2019;euros les d\u0026#x00E9;penses indirectes et induites, soit un total de pr\u0026#x00E8;s de 1,9 milliards d\u0026#x2019;euros pour une d\u0026#x00E9;pense fiscale de 254 millions d\u0026#x2019;euros. Cela repr\u0026#x00E9;sente 3,75\u0026nbsp;euros de d\u0026#x00E9;penses directes pour 1\u0026nbsp;euro de cr\u0026#x00E9;dit d\u0026#x2019;imp\u0026#x00F4;t, et 7,4\u0026nbsp;euros de d\u0026#x00E9;penses totales pour 1\u0026nbsp;euro de cr\u0026#x00E9;dit d\u0026#x2019;imp\u0026#x00F4;t. Ce m\u0026#x00EA;me euro a g\u0026#x00E9;n\u0026#x00E9;r\u0026#x00E9; 1,31\u0026nbsp;euros de recettes fiscales et sociales directes.\u003C\/p\u003E\u003Cp style=\u0022text-align: justify;\u0022\u003EEntre 2017 et 2023, plus de 3 milliards d\u0026#x2019;euros de d\u0026#x00E9;penses directes, et un montant \u0026#x00E9;quivalent de d\u0026#x00E9;penses non \u0026#x00E9;ligibles ou indirectes, soit un total de 6 milliards d\u0026#x2019;euros, ont \u0026#x00E9;t\u0026#x00E9; d\u0026#x00E9;pens\u0026#x00E9;s en France. Sans ce dispositif, ces sommes auraient \u0026#x00E9;t\u0026#x00E9; d\u0026#x00E9;pens\u0026#x00E9;es dans un autre pays.\u003C\/p\u003E\u003Cp style=\u0022text-align: justify;\u0022\u003EChaque film ou s\u0026#x00E9;rie concern\u0026#x00E9; mobilise des dizaines, parfois des centaines de prestataires locaux. Il s\u0026#x2019;agit d\u0026#x2019;une v\u0026#x00E9;ritable \u0026#x00E9;conomie de proximit\u0026#x00E9;, avec un effet multiplicateur fort sur les territoires, qui soutient des secteurs d\u0026#x2019;activit\u0026#x00E9; au-del\u0026#x00E0; du cin\u0026#x00E9;ma, tels que l\u0026#x2019;h\u0026#x00F4;tellerie, la restauration, les artisans du b\u0026#x00E2;timent, les loueurs de mat\u0026#x00E9;riel, la logistique.\u003C\/p\u003E\u003Cp style=\u0022text-align: justify;\u0022\u003EAu-del\u0026#x00E0;, ces productions contribuent directement au soft power de notre pays et en particulier \u0026#x00E0; l\u0026#x2019;attractivit\u0026#x00E9; touristique France. Les \u0026#x00E9;tudes montrent par exemple que trois quarts des visiteurs \u0026#x00E9;trangers interrog\u0026#x00E9;s d\u0026#x00E9;claraient qu\u0026#x2019;une \u0026#x0153;uvre repr\u0026#x00E9;sentant notre pays leur avait donn\u0026#x00E9; envie de visiter la France.\u003C\/p\u003E\u003Cp style=\u0022text-align: justify;\u0022\u003ELes projets internationaux vis\u0026#x00E9;s par ce cr\u0026#x00E9;dit d\u0026#x2019;imp\u0026#x00F4;t, compte tenu de leur ampleur et des temps de pr\u0026#x00E9;paration incompressibles, n\u0026#x00E9;cessitent une pr\u0026#x00E9;paration avec un calendrier anticip\u0026#x00E9;. Ainsi, en pratique, pour les films ayant vocation \u0026#x00E0; \u0026#x00EA;tre tourn\u0026#x00E9;s en 2027 ou 2028, les d\u0026#x00E9;cisions seront prises d\u0026#x00E8;s 2026.\u003C\/p\u003E\u003Cp style=\u0022text-align: justify;\u0022\u003EOr, actuellement, le C2I est born\u0026#x00E9; aux d\u0026#x00E9;penses r\u0026#x00E9;alis\u0026#x00E9;es avant le 31\u0026nbsp;d\u0026#x00E9;cembre\u0026nbsp;2026. Pour \u0026#x00E9;viter l\u0026#x2019;incertitude induite par ce bornage, il est indispensable de le prolonger par anticipation jusqu\u0026#x2019;au\u0026nbsp;31\u0026nbsp;d\u0026#x00E9;cembre\u0026nbsp;2031 afin de donner la visibilit\u0026#x00E9; suffisante pour la d\u0026#x00E9;cision et la r\u0026#x00E9;alisation, faute de quoi les productions en train d\u0026#x2019;\u0026#x00EA;tre d\u0026#x00E9;cid\u0026#x00E9;es \u0026#x00E9;chapperont \u0026#x00E0; la France.\u003C\/p\u003E\u003Cp style=\u0022text-align: justify;\u0022\u003ECet amendement vise donc \u0026#x00E0; proroger ce cr\u0026#x00E9;dit d\u0026#x2019;imp\u0026#x00F4;t jusqu\u0026#x2019;au\u0026nbsp;31\u0026nbsp;d\u0026#x00E9;cembre\u0026nbsp;2031 afin de s\u0026#x00E9;curiser le cadre fiscal applicable \u0026#x00E0; ces productions internationales et de donner de la visibilit\u0026#x00E9; aux investisseurs \u0026#x00E9;trangers, dans un contexte de concurrence internationale accrue. Cette prorogation n\u0026#x2019;induit aucun co\u0026#x00FB;t suppl\u0026#x00E9;mentaire pour 2026.\u003C\/p\u003E\u003Cp style=\u0022text-align: justify;\u0022\u003ECet amendement a \u0026#x00E9;t\u0026#x00E9; travaill\u0026#x00E9; avec la F\u0026#x00E9;d\u0026#x00E9;ration des industries du Cin\u0026#x00E9;ma, de l\u0026#x2019;Audiovisuel et du Multim\u0026#x00E9;dia.\u003C\/p\u003E","annexeExposeSommaire":{}}},"cycleDeVie":{"dateDepot":"2025-10-16","datePublication":"2025-10-18","soumisArticle40":"false","etatDesTraitements":{"etat":{"code":"ET","libelle":"En traitement"},"sousEtat":{}},"dateSort":{},"sort":{}},"representations":{"representation":{"nom":"PDF","typeMime":{"type":"application","subType":"PDF"},"statutRepresentation":{"verbatim":"true","canonique":"true","officielle":"true","transcription":"false","enregistrement":"false"},"repSource":{},"offset":{},"contenu":{"documentURI":"\/base\/AMANR5L17PO59048B1906P1D1N000035?format=pdf"},"dateDispoRepresentation":{}}},"seanceDiscussionRef":{},"article99":"false","loiReference":{"codeLoi":"CGI","divisionCodeLoi":"220 quaterdecies"},"discussionCommune":{},"discussionIdentique":{},"accordGouvernementDepotHorsDelai":"Sans objet"}